{
  "id": "daf74874-2512-4165-8340-d900191228fa",
  "prevId": "00000000-0000-0000-0000-000000000000",
  "version": "7",
  "dialect": "postgresql",
  "tables": {
    "public.competitors": {
      "name": "competitors",
      "schema": "",
      "columns": {
        "id": {
          "name": "id",
          "type": "uuid",
          "primaryKey": true,
          "notNull": true,
          "default": "gen_random_uuid()"
        },
        "name": {
          "name": "name",
          "type": "text",
          "primaryKey": false,
          "notNull": true
        },
        "domain": {
          "name": "domain",
          "type": "text",
          "primaryKey": false,
          "notNull": true
        },
        "created_at": {
          "name": "created_at",
          "type": "timestamp",
          "primaryKey": false,
          "notNull": true,
          "default": "now()"
        }
      },
      "indexes": {},
      "foreignKeys": {},
      "compositePrimaryKeys": {},
      "uniqueConstraints": {},
      "policies": {},
      "checkConstraints": {},
      "isRLSEnabled": false
    },
    "public.intel_items": {
      "name": "intel_items",
      "schema": "",
      "columns": {
        "id": {
          "name": "id",
          "type": "uuid",
          "primaryKey": true,
          "notNull": true,
          "default": "gen_random_uuid()"
        },
        "title": {
          "name": "title",
          "type": "text",
          "primaryKey": false,
          "notNull": true
        },
        "raw_content": {
          "name": "raw_content",
          "type": "text",
          "primaryKey": false,
          "notNull": true
        },
        "source_url": {
          "name": "source_url",
          "type": "text",
          "primaryKey": false,
          "notNull": true
        },
        "source_platform": {
          "name": "source_platform",
          "type": "text",
          "primaryKey": false,
          "notNull": true
        },
        "signal_type": {
          "name": "signal_type",
          "type": "text",
          "primaryKey": false,
          "notNull": true
        },
        "competitor_id": {
          "name": "competitor_id",
          "type": "uuid",
          "primaryKey": false,
          "notNull": false
        },
        "keyword_id": {
          "name": "keyword_id",
          "type": "uuid",
          "primaryKey": false,
          "notNull": false
        },
        "created_at": {
          "name": "created_at",
          "type": "timestamp",
          "primaryKey": false,
          "notNull": true,
          "default": "now()"
        }
      },
      "indexes": {
        "intel_items_created_at_idx": {
          "name": "intel_items_created_at_idx",
          "columns": [
            {
              "expression": "created_at",
              "isExpression": false,
              "asc": true,
              "nulls": "last"
            }
          ],
          "isUnique": false,
          "concurrently": false,
          "method": "btree",
          "with": {}
        }
      },
      "foreignKeys": {
        "intel_items_competitor_id_competitors_id_fk": {
          "name": "intel_items_competitor_id_competitors_id_fk",
          "tableFrom": "intel_items",
          "tableTo": "competitors",
          "columnsFrom": [
            "competitor_id"
          ],
          "columnsTo": [
            "id"
          ],
          "onDelete": "no action",
          "onUpdate": "no action"
        },
        "intel_items_keyword_id_keywords_id_fk": {
          "name": "intel_items_keyword_id_keywords_id_fk",
          "tableFrom": "intel_items",
          "tableTo": "keywords",
          "columnsFrom": [
            "keyword_id"
          ],
          "columnsTo": [
            "id"
          ],
          "onDelete": "no action",
          "onUpdate": "no action"
        }
      },
      "compositePrimaryKeys": {},
      "uniqueConstraints": {},
      "policies": {},
      "checkConstraints": {},
      "isRLSEnabled": false
    },
    "public.keywords": {
      "name": "keywords",
      "schema": "",
      "columns": {
        "id": {
          "name": "id",
          "type": "uuid",
          "primaryKey": true,
          "notNull": true,
          "default": "gen_random_uuid()"
        },
        "term": {
          "name": "term",
          "type": "text",
          "primaryKey": false,
          "notNull": true
        },
        "category": {
          "name": "category",
          "type": "text",
          "primaryKey": false,
          "notNull": true
        },
        "created_at": {
          "name": "created_at",
          "type": "timestamp",
          "primaryKey": false,
          "notNull": true,
          "default": "now()"
        }
      },
      "indexes": {},
      "foreignKeys": {},
      "compositePrimaryKeys": {},
      "uniqueConstraints": {},
      "policies": {},
      "checkConstraints": {},
      "isRLSEnabled": false
    }
  },
  "enums": {},
  "schemas": {},
  "sequences": {},
  "roles": {},
  "policies": {},
  "views": {},
  "_meta": {
    "columns": {},
    "schemas": {},
    "tables": {}
  }
}